fuse/__init__.py
procfuse-0.0.2.dist-info/METADATA
procfuse-0.0.2.dist-info/WHEEL
procfuse-0.0.2.dist-info/top_level.txt
procfuse-0.0.2.dist-info/RECORD
