Metadata-Version: 2.1
Name: procfuse
Version: 0.0.2
Summary: Proc Fuse Module.
Home-page: UNKNOWN
Author: TunaFish2K
Author-email: tunafish2k@163.com
License: Apache-2.0
Platform: UNKNOWN
